{
    "appKeys": {
        "KEY_BACKGROUND_COLOR": 2,
        "KEY_TIME_COLOR": 0,
        "KEY_VIBRATE_ON_DISCONNECT": 1
    },
    "capabilities": [
        "configurable"
    ],
    "companyName": "clach04",
    "longName": "Captain Minion inverted",
    "projectType": "native",
    "resources": {
        "media": [
            {
                "file": "images/capnion_icon.png",
                "menuIcon": true,
                "name": "IMAGE_ICON",
                "type": "png"
            },
            {
                "file": "images/capnion.png",
                "name": "IMAGE_CAPNION",
                "type": "png"
            }
        ]
    },
    "sdkVersion": "3",
    "shortName": "CapNion inv",
    "targetPlatforms": [
        "basalt"
    ],
    "uuid": "7df75c8c-223a-4c8c-a84f-a8eaf56c5bd3",
    "versionLabel": "0.1",
    "watchapp": {
        "watchface": true
    }
}
